browseek/__init__.py
browseek/authorization_router.py
browseek/browser_instance.py
browseek/browser_router.py
browseek/captcha_solver.py
browseek/device_profile.py
browseek/driver_router.py
browseek/exceptions.py
browseek/network_config.py
browseek/request_interceptor.py
browseek-0.1.7.dist-info/LICENSE
browseek-0.1.7.dist-info/METADATA
browseek-0.1.7.dist-info/WHEEL
browseek-0.1.7.dist-info/top_level.txt
browseek-0.1.7.dist-info/RECORD
