Metadata-Version: 2.1
Name: browseek
Version: 0.1.7
Summary: Advanced multi-browser automation library
Home-page: https://www.browseek.com
Author: Tom Sapletta
Author-email: info@softreck.dev
Classifier: Development Status :: 3 - Alpha
Classifier: Intended Audience :: Developers
Classifier: License :: OSI Approved :: Apache Software License
Classifier: Operating System :: OS Independent
Classifier: Programming Language :: Python :: 3
Classifier: Programming Language :: Python :: 3.6
Classifier: Programming Language :: Python :: 3.7
Classifier: Programming Language :: Python :: 3.8
Classifier: Programming Language :: Python :: 3.9
License-File: LICENSE
